{
  "list": [
    {
      "id": "224471",
      "name": "3 Chicken Wings",
      "price": "250.00"
    },
    {
      "id": "224474",
      "name": "Chicken Livers and Portuguese Roll",
      "price": "250.00"
    },
    {
      "id": "224477",
      "name": "Spicy Mixed Olives (V)",
      "price": "215.00"
    },
    {
      "id": "224480",
      "name": "Hummus with PERI-PERI Drizzle",
      "price": "215.00"
    },
    {
      "id": "224483",
      "name": "Red Pepper Dip",
      "price": "205.00"
    },
    {
      "id": "224486",
      "name": "Appeteaser Platter",
      "price": "615.00"
    },
    {
      "id": "224489",
      "name": "All Together Now",
      "price": "520.00"
    },
    {
      "id": "224543",
      "name": "On its own",
      "price": "385.00"
    },
    {
      "id": "224546",
      "name": "With 1 Regular Side",
      "price": "485.00"
    }
  ]
}
